tuple_flatten/__init__.py
tuple_flatten-1.0.dist-info/LICENSE.txt
tuple_flatten-1.0.dist-info/METADATA
tuple_flatten-1.0.dist-info/WHEEL
tuple_flatten-1.0.dist-info/top_level.txt
tuple_flatten-1.0.dist-info/RECORD
