Metadata-Version: 2.1
Name: tuple-flatten
Version: 1.0
Summary: Basically only a function to iterate through tuples and add their values. Example: (1,2)+(2,3)=(3,5)
Home-page: UNKNOWN
Author: El Sholz
Author-email: fewav@braun4email.com
License: UNKNOWN
Platform: UNKNOWN
Classifier: Programming Language :: Python :: 3
Classifier: License :: OSI Approved :: GNU General Public License v3 or later (GPLv3+)
Classifier: Operating System :: OS Independent
